LICENSE
MANIFEST.in
README.rst
setup.py
test.py
fedmsg.d/config.py
fedmsg_atomic_composer/__init__.py
fedmsg_atomic_composer/cli.py
fedmsg_atomic_composer/composer.py
fedmsg_atomic_composer/config.py
fedmsg_atomic_composer/consumer.py
fedmsg_atomic_composer.egg-info/PKG-INFO
fedmsg_atomic_composer.egg-info/SOURCES.txt
fedmsg_atomic_composer.egg-info/dependency_links.txt
fedmsg_atomic_composer.egg-info/entry_points.txt
fedmsg_atomic_composer.egg-info/requires.txt
fedmsg_atomic_composer.egg-info/top_level.txt
fedmsg_atomic_composer/templates/mock.mako
fedmsg_atomic_composer/templates/repo.mako
rpm/fedmsg-atomic-composer.spec
systemd/fedmsg-atomic-composer.service