Metadata-Version: 1.0
Name: fedmsg-atomic-composer
Version: 2017.1.0
Summary: Composes Atomic rpm-ostrees when Fedora repositories are updated
Home-page: https://github.com/fedora-infra/fedmsg-atomic-composer
Author: Luke Macken
Author-email: lmacken@redhat.com
License: GPLv3
Platform: UNKNOWN
